secure_media_processor-2.1.0.dist-info/licenses/LICENSE
src/__init__.py
src/cli.py
src/cloud_storage.py
src/config.py
src/dicom_processor.py
src/encryption.py
src/gpu_processor.py
src/license_manager.py
src/medical_preprocessing.py
src/ml_inference.py
src/rate_limiter.py
src/unet_segmentation.py
src/cli/__init__.py
src/cli/cloud.py
src/cli/crypto.py
src/cli/license.py
src/cli/main.py
src/cli/media.py
src/cli/medical.py
src/cloud/__init__.py
src/cloud/legacy.py
src/cloud/connectors/__init__.py
src/cloud/connectors/base.py
src/cloud/connectors/dropbox.py
src/cloud/connectors/google_drive.py
src/cloud/connectors/manager.py
src/cloud/connectors/s3.py
src/connectors/__init__.py
src/connectors/base_connector.py
src/connectors/connector_manager.py
src/connectors/dropbox_connector.py
src/connectors/google_drive_connector.py
src/connectors/s3_connector.py
src/core/__init__.py
src/core/audit_logger.py
src/core/config.py
src/core/encryption.py
src/core/key_exchange.py
src/core/rate_limiter.py
src/core/secure_transfer.py
src/licensing/__init__.py
src/licensing/manager.py
src/medical/__init__.py
src/medical/dicom.py
src/medical/pipeline.py
src/medical/preprocessing.py
src/medical/inference/__init__.py
src/medical/inference/config.py
src/medical/inference/loaders.py
src/medical/inference/pipeline.py
src/medical/unet/__init__.py
src/medical/unet/config.py
src/medical/unet/inference.py
src/medical/unet/losses.py
src/medical/unet/metrics.py
src/medical/unet/models.py
src/medical/unet/postprocessing.py
src/processing/__init__.py
src/processing/gpu.py
secure_media_processor-2.1.0.dist-info/METADATA
secure_media_processor-2.1.0.dist-info/WHEEL
secure_media_processor-2.1.0.dist-info/entry_points.txt
secure_media_processor-2.1.0.dist-info/top_level.txt
secure_media_processor-2.1.0.dist-info/RECORD
