Metadata-Version: 2.4
Name: secure-media-processor
Version: 2.1.0
Summary: Secure data pipeline for transferring sensitive data from cloud to local GPU processing
Author-email: Ihab Saloum <Isaloum@users.noreply.github.com>
Maintainer-email: Ihab Saloum <Isaloum@users.noreply.github.com>
License-Expression: MIT
Project-URL: Homepage, https://github.com/Isaloum/Secure-Media-Processor
Project-URL: Documentation, https://github.com/Isaloum/Secure-Media-Processor#readme
Project-URL: Repository, https://github.com/Isaloum/Secure-Media-Processor.git
Project-URL: Bug Tracker, https://github.com/Isaloum/Secure-Media-Processor/issues
Project-URL: Changelog, https://github.com/Isaloum/Secure-Media-Processor/releases
Keywords: encryption,aes-256-gcm,cloud-storage,aws-s3,google-drive,dropbox,gpu-acceleration,media-processing,privacy,security
Classifier: Development Status :: 5 - Production/Stable
Classifier: Intended Audience :: Developers
Classifier: Intended Audience :: End Users/Desktop
Classifier: Operating System :: OS Independent
Classifier: Programming Language :: Python :: 3
Classifier: Programming Language :: Python :: 3.8
Classifier: Programming Language :: Python :: 3.9
Classifier: Programming Language :: Python :: 3.10
Classifier: Programming Language :: Python :: 3.11
Classifier: Programming Language :: Python :: 3.12
Classifier: Topic :: Security :: Cryptography
Classifier: Topic :: System :: Archiving :: Backup
Classifier: Topic :: Multimedia :: Graphics
Classifier: Topic :: Multimedia :: Video
Requires-Python: >=3.8
License-File: LICENSE
Requires-Dist: cryptography>=41.0.7
Requires-Dist: python-dotenv>=1.0.0
Requires-Dist: pydantic>=2.5.0
Requires-Dist: pydantic-settings>=2.1.0
Requires-Dist: boto3>=1.34.0
Requires-Dist: google-cloud-storage>=2.14.0
Requires-Dist: google-api-python-client>=2.111.0
Requires-Dist: google-auth-httplib2>=0.2.0
Requires-Dist: google-auth-oauthlib>=1.2.0
Requires-Dist: dropbox>=11.36.2
Requires-Dist: opencv-python>=4.9.0.80
Requires-Dist: Pillow>=10.2.0
Requires-Dist: numpy>=1.26.0
Requires-Dist: click>=8.1.7
Requires-Dist: tqdm>=4.66.1
Requires-Dist: colorama>=0.4.6
Provides-Extra: dev
Requires-Dist: pytest>=7.4.3; extra == "dev"
Requires-Dist: pytest-cov>=4.1.0; extra == "dev"
Requires-Dist: black>=23.0.0; extra == "dev"
Requires-Dist: flake8>=6.0.0; extra == "dev"
Requires-Dist: mypy>=1.0.0; extra == "dev"
Provides-Extra: gpu
Requires-Dist: torch>=2.1.2; extra == "gpu"
Requires-Dist: torchvision>=0.16.2; extra == "gpu"
Provides-Extra: medical
Requires-Dist: pydicom>=2.4.0; extra == "medical"
Requires-Dist: nibabel>=5.2.0; extra == "medical"
Requires-Dist: scipy>=1.11.0; extra == "medical"
Requires-Dist: scikit-image>=0.22.0; extra == "medical"
Provides-Extra: all
Requires-Dist: torch>=2.1.2; extra == "all"
Requires-Dist: torchvision>=0.16.2; extra == "all"
Requires-Dist: pydicom>=2.4.0; extra == "all"
Requires-Dist: nibabel>=5.2.0; extra == "all"
Requires-Dist: scipy>=1.11.0; extra == "all"
Requires-Dist: scikit-image>=0.22.0; extra == "all"
Requires-Dist: onnxruntime>=1.16.0; extra == "all"
Dynamic: license-file
